irholiday/__init__.py
irholiday/core.py
irholiday/utils.py
irholiday-0.1.8.data/scripts/irholiday2csv
irholiday-0.1.8.dist-info/AUTHORS.rst
irholiday-0.1.8.dist-info/LICENSE
irholiday-0.1.8.dist-info/METADATA
irholiday-0.1.8.dist-info/WHEEL
irholiday-0.1.8.dist-info/top_level.txt
irholiday-0.1.8.dist-info/RECORD
