Metadata-Version: 2.1
Name: irholiday
Version: 0.1.8
Summary: Pandas Datafarme data from time.ir
Home-page: https://github.com/hadi-gharibi/irholiday
Author: hadi gharibi
Author-email: hady.gharibi@gmail.com
License: MIT license
Keywords: irholiday
Platform: UNKNOWN
Classifier: Development Status :: 2 - Pre-Alpha
Classifier: Intended Audience :: Developers
Classifier: License :: OSI Approved :: MIT License
Classifier: Natural Language :: English
Classifier: Programming Language :: Python :: 3
Classifier: Programming Language :: Python :: 3.4
Classifier: Programming Language :: Python :: 3.5
Classifier: Programming Language :: Python :: 3.6
Classifier: Programming Language :: Python :: 3.7
Classifier: Programming Language :: Python :: 3.8
Classifier: Programming Language :: Python :: 3.9
Requires-Dist: beautifulsoup4
Requires-Dist: convert-numbers
Requires-Dist: convertdate
Requires-Dist: jdatetime
Requires-Dist: pandas
Requires-Dist: requests
Requires-Dist: umalqurra
